README.md
README.rst
setup.py
fc/__init__.py
fc/fc.py
fc.egg-info/PKG-INFO
fc.egg-info/SOURCES.txt
fc.egg-info/dependency_links.txt
fc.egg-info/top_level.txt
tests/__init__.py
tests/test_fc.py